skyline_prism/__init__.py
skyline_prism/batch_correction.py
skyline_prism/chunked_processing.py
skyline_prism/cli.py
skyline_prism/data_io.py
skyline_prism/fasta.py
skyline_prism/normalization.py
skyline_prism/parsimony.py
skyline_prism/rollup.py
skyline_prism/transition_rollup.py
skyline_prism/validation.py
skyline_prism/visualization.py
skyline_prism-0.1.0.dist-info/METADATA
skyline_prism-0.1.0.dist-info/WHEEL
skyline_prism-0.1.0.dist-info/entry_points.txt
skyline_prism-0.1.0.dist-info/licenses/LICENSE
skyline_prism-0.1.0.dist-info/RECORD
