Metadata-Version: 2.4
Name: skyline-prism
Version: 0.1.0
Summary: PRISM (Proteomics Reference-Integrated Signal Modeling) - RT-aware normalization for Skyline proteomics data
Project-URL: Homepage, https://github.com/maccoss/skyline-prism
Project-URL: Documentation, https://github.com/maccoss/skyline-prism#readme
Project-URL: Repository, https://github.com/maccoss/skyline-prism
Project-URL: Skyline, https://skyline.ms
Author-email: MacCoss Lab <maccoss@uw.edu>
License-Expression: MIT
License-File: LICENSE
Keywords: mass-spectrometry,normalization,proteomics,quantification
Classifier: Development Status :: 3 - Alpha
Classifier: Intended Audience :: Science/Research
Classifier: License :: OSI Approved :: MIT License
Classifier: Programming Language :: Python :: 3
Classifier: Programming Language :: Python :: 3.9
Classifier: Programming Language :: Python :: 3.10
Classifier: Programming Language :: Python :: 3.11
Classifier: Programming Language :: Python :: 3.12
Classifier: Topic :: Scientific/Engineering :: Bio-Informatics
Requires-Python: >=3.9
Requires-Dist: duckdb>=0.9
Requires-Dist: numpy>=1.21
Requires-Dist: pandas>=1.4
Requires-Dist: pyarrow>=8.0
Requires-Dist: pyyaml>=6.0
Requires-Dist: scikit-learn>=1.0
Requires-Dist: scipy>=1.7
Provides-Extra: dev
Requires-Dist: black>=23.0; extra == 'dev'
Requires-Dist: mypy>=1.0; extra == 'dev'
Requires-Dist: pytest-cov>=4.0; extra == 'dev'
Requires-Dist: pytest>=7.0; extra == 'dev'
Requires-Dist: ruff>=0.1; extra == 'dev'
Provides-Extra: viz
Requires-Dist: matplotlib>=3.5; extra == 'viz'
Requires-Dist: plotnine>=0.12; extra == 'viz'
Requires-Dist: seaborn>=0.12; extra == 'viz'
